mpv_yt/__init__.py
mpv_yt/cli.py
mpv_yt/youtube.py
mpv_yt/youtube_parser.py
mpv_yt-1.0.1.dist-info/METADATA
mpv_yt-1.0.1.dist-info/WHEEL
mpv_yt-1.0.1.dist-info/entry_points.txt
mpv_yt-1.0.1.dist-info/top_level.txt
mpv_yt-1.0.1.dist-info/RECORD
