Metadata-Version: 2.4
Name: mpv-yt
Version: 1.0.1
Summary: High-performance YouTube video streaming with mpv
Author: Mustafa Chyi
Project-URL: Repository, https://github.com/mustafachyi/mpv-yt
Classifier: Development Status :: 5 - Production/Stable
Classifier: Environment :: Console
Classifier: Intended Audience :: End Users/Desktop
Classifier: License :: OSI Approved :: MIT License
Classifier: Operating System :: OS Independent
Classifier: Programming Language :: Python :: 3.9
Classifier: Programming Language :: Python :: 3.10
Classifier: Programming Language :: Python :: 3.11
Classifier: Programming Language :: Python :: 3.12
Classifier: Programming Language :: Python :: 3.13
Classifier: Topic :: Multimedia :: Video :: Display
Requires-Python: >=3.9
Requires-Dist: httpx[brotli,http2]>=0.28.1
Requires-Dist: anyio>=4.10.0
Requires-Dist: orjson>=3.11.3
